{
  "id": 139,
  "slug": "happy-number",
  "title": "Happy Number",
  "difficulty": "Easy",
  "tags": [
    "Hash Table",
    "Math",
    "Two Pointers"
  ],
  "companies": [],
  "statement": "# Happy Number\n\nRepeatedly replace a number by the sum of squares of its digits. Return whether the process reaches 1.\n\n## Examples\n\n**Example 1**\n\n```text\nInput: n = 19\nOutput: true\n```\n\n**Example 2**\n\n```text\nInput: n = 2\nOutput: false\n```\n\n**Example 3**\n\n```text\nInput: n = 1\nOutput: true\n```\n\n## Constraints\n\n- Inputs are sized for local offline execution.\n- Return the value described by the method signature.",
  "editorial": "Use direct arithmetic, matrix indexing, or bit operations to preserve the required invariants while keeping extra state small.",
  "solution_notes": "```python\nclass Solution:\n    def isHappy(self, n):\n        seen = set()\n        while n != 1 and n not in seen:\n            seen.add(n)\n            n = sum(int(ch) ** 2 for ch in str(n))\n        return n == 1\n```",
  "hints": [
    "Watch fixed-width integer boundaries where the prompt requires them.",
    "For matrix mutation, mark or capture affected rows and columns before overwriting."
  ],
  "starter_code": {
    "python": "class Solution:\n    def isHappy(self, n):\n        pass\n"
  },
  "entrypoint": {
    "class_name": "Solution",
    "method_name": "isHappy"
  },
  "checker": {
    "type": "exact"
  },
  "time_limit_ms": 2500,
  "memory_limit_mb": 256,
  "cases": [
    {
      "id": "case-1",
      "name": "Case 1",
      "input": {
        "n": 19
      },
      "expected": true,
      "hidden": false
    },
    {
      "id": "case-2",
      "name": "Case 2",
      "input": {
        "n": 2
      },
      "expected": false,
      "hidden": false
    },
    {
      "id": "case-3",
      "name": "Case 3",
      "input": {
        "n": 1
      },
      "expected": true,
      "hidden": false
    },
    {
      "id": "hidden-1",
      "name": "Hidden Case 1",
      "input": {
        "n": 38
      },
      "expected": false,
      "hidden": true
    },
    {
      "id": "hidden-2",
      "name": "Hidden Case 2",
      "input": {
        "n": 75
      },
      "expected": false,
      "hidden": true
    },
    {
      "id": "hidden-3",
      "name": "Hidden Case 3",
      "input": {
        "n": 112
      },
      "expected": false,
      "hidden": true
    },
    {
      "id": "hidden-4",
      "name": "Hidden Case 4",
      "input": {
        "n": 149
      },
      "expected": false,
      "hidden": true
    },
    {
      "id": "hidden-5",
      "name": "Hidden Case 5",
      "input": {
        "n": 186
      },
      "expected": false,
      "hidden": true
    },
    {
      "id": "hidden-6",
      "name": "Hidden Case 6",
      "input": {
        "n": 223
      },
      "expected": false,
      "hidden": true
    },
    {
      "id": "hidden-7",
      "name": "Hidden Case 7",
      "input": {
        "n": 260
      },
      "expected": false,
      "hidden": true
    },
    {
      "id": "hidden-8",
      "name": "Hidden Case 8",
      "input": {
        "n": 297
      },
      "expected": false,
      "hidden": true
    },
    {
      "id": "hidden-9",
      "name": "Hidden Case 9",
      "input": {
        "n": 334
      },
      "expected": false,
      "hidden": true
    },
    {
      "id": "hidden-10",
      "name": "Hidden Case 10",
      "input": {
        "n": 371
      },
      "expected": false,
      "hidden": true
    },
    {
      "id": "hidden-11",
      "name": "Hidden Case 11",
      "input": {
        "n": 408
      },
      "expected": false,
      "hidden": true
    },
    {
      "id": "hidden-12",
      "name": "Hidden Case 12",
      "input": {
        "n": 445
      },
      "expected": false,
      "hidden": true
    },
    {
      "id": "hidden-13",
      "name": "Hidden Case 13",
      "input": {
        "n": 482
      },
      "expected": false,
      "hidden": true
    },
    {
      "id": "hidden-14",
      "name": "Hidden Case 14",
      "input": {
        "n": 19
      },
      "expected": true,
      "hidden": true
    },
    {
      "id": "hidden-15",
      "name": "Hidden Case 15",
      "input": {
        "n": 56
      },
      "expected": false,
      "hidden": true
    },
    {
      "id": "hidden-16",
      "name": "Hidden Case 16",
      "input": {
        "n": 93
      },
      "expected": false,
      "hidden": true
    },
    {
      "id": "hidden-17",
      "name": "Hidden Case 17",
      "input": {
        "n": 130
      },
      "expected": true,
      "hidden": true
    },
    {
      "id": "hidden-18",
      "name": "Hidden Case 18",
      "input": {
        "n": 167
      },
      "expected": true,
      "hidden": true
    },
    {
      "id": "hidden-19",
      "name": "Hidden Case 19",
      "input": {
        "n": 204
      },
      "expected": false,
      "hidden": true
    },
    {
      "id": "hidden-20",
      "name": "Hidden Case 20",
      "input": {
        "n": 241
      },
      "expected": false,
      "hidden": true
    },
    {
      "id": "hidden-21",
      "name": "Hidden Case 21",
      "input": {
        "n": 278
      },
      "expected": false,
      "hidden": true
    }
  ]
}
